tocPDF/__init__.py
tocPDF/__main__.py
tocPDF/tocPDF.py
tocPDF-0.3.10.dist-info/LICENSE
tocPDF-0.3.10.dist-info/METADATA
tocPDF-0.3.10.dist-info/WHEEL
tocPDF-0.3.10.dist-info/entry_points.txt
tocPDF-0.3.10.dist-info/top_level.txt
tocPDF-0.3.10.dist-info/RECORD
