Metadata-Version: 2.1
Name: tocPDF
Version: 0.3.10
Summary: A bookmark generator for pdf
Author-email: Kalman Szenes <szenes.kalman@gmail.com>
License: MIT License
Project-URL: Repository, https://github.com/kszenes/tocPDF
Classifier: Programming Language :: Python :: 3
Classifier: Operating System :: OS Independent
License-File: LICENSE
Requires-Dist: pypdf
Requires-Dist: tika
Requires-Dist: click
Requires-Dist: pdfplumber
Requires-Dist: tqdm
Provides-Extra: dev
Requires-Dist: pytest; extra == "dev"
